examples/basic_examples.py
examples/example_utils.py
examples/sqlalchemy_api_examples.py
sqlalchemy_kinetica/custom_commands.py
sqlalchemy_kinetica/dialect.py
sqlalchemy_kinetica/kinetica_types.py
sqlalchemy_kinetica-7.2.3.1.dist-info/licenses/LICENSE
sqlalchemy_kinetica-7.2.3.1.dist-info/METADATA
sqlalchemy_kinetica-7.2.3.1.dist-info/WHEEL
sqlalchemy_kinetica-7.2.3.1.dist-info/entry_points.txt
sqlalchemy_kinetica-7.2.3.1.dist-info/top_level.txt
sqlalchemy_kinetica-7.2.3.1.dist-info/RECORD
