Metadata-Version: 2.4
Name: sqlalchemy-kinetica
Version: 7.2.3.1
Summary: Kinetica Dialect for SQLAlchemy
Author-email: "Kinetica DB, Inc." <support@kinetica.com>
License: MIT License
Project-URL: Homepage, https://www.kinetica.com
Project-URL: Documentation, https://docs.kinetica.com/7.2/api/python/
Keywords: kinetica,gpudb
Classifier: Programming Language :: Python :: 3
Classifier: Topic :: Database
Requires-Python: >=3.8
License-File: LICENSE
Requires-Dist: sqlalchemy<2.0.40,>=2.0.31
Requires-Dist: gpudb>=7.2.3.0
Requires-Dist: shapely>=2.0.5
Requires-Dist: geojson>=3.1.0
Dynamic: license-file
